build/lib/build/lib/build/lib/build/lib/neo_whisper/__init__.py
build/lib/build/lib/build/lib/build/lib/neo_whisper/_version.py
build/lib/build/lib/build/lib/build/lib/neo_whisper/common.py
build/lib/build/lib/build/lib/build/lib/neo_whisper/decoding.py
build/lib/build/lib/build/lib/build/lib/neo_whisper/model.py
build/lib/build/lib/build/lib/build/lib/neo_whisper/nn_utils.py
build/lib/build/lib/build/lib/build/lib/neo_whisper/tokenizer.py
build/lib/build/lib/build/lib/build/lib/neo_whisper/transcribe.py
build/lib/build/lib/build/lib/build/lib/neo_whisper/whisper.py
build/lib/build/lib/build/lib/neo_whisper/__init__.py
build/lib/build/lib/build/lib/neo_whisper/_version.py
build/lib/build/lib/build/lib/neo_whisper/common.py
build/lib/build/lib/build/lib/neo_whisper/decoding.py
build/lib/build/lib/build/lib/neo_whisper/model.py
build/lib/build/lib/build/lib/neo_whisper/nn_utils.py
build/lib/build/lib/build/lib/neo_whisper/tokenizer.py
build/lib/build/lib/build/lib/neo_whisper/transcribe.py
build/lib/build/lib/build/lib/neo_whisper/whisper.py
build/lib/build/lib/neo_whisper/__init__.py
build/lib/build/lib/neo_whisper/_version.py
build/lib/build/lib/neo_whisper/common.py
build/lib/build/lib/neo_whisper/decoding.py
build/lib/build/lib/neo_whisper/model.py
build/lib/build/lib/neo_whisper/nn_utils.py
build/lib/build/lib/neo_whisper/tokenizer.py
build/lib/build/lib/neo_whisper/transcribe.py
build/lib/build/lib/neo_whisper/whisper.py
build/lib/neo_whisper/__init__.py
build/lib/neo_whisper/_version.py
build/lib/neo_whisper/common.py
build/lib/neo_whisper/decoding.py
build/lib/neo_whisper/model.py
build/lib/neo_whisper/nn_utils.py
build/lib/neo_whisper/tokenizer.py
build/lib/neo_whisper/transcribe.py
build/lib/neo_whisper/whisper.py
neo_whisper/__init__.py
neo_whisper/_version.py
neo_whisper/common.py
neo_whisper/decoding.py
neo_whisper/model.py
neo_whisper/nn_utils.py
neo_whisper/tokenizer.py
neo_whisper/transcribe.py
neo_whisper/whisper.py
neo_whisper-0.0.3.dist-info/licenses/LICENSE
neo_whisper-0.0.3.dist-info/METADATA
neo_whisper-0.0.3.dist-info/WHEEL
neo_whisper-0.0.3.dist-info/top_level.txt
neo_whisper-0.0.3.dist-info/RECORD
