Metadata-Version: 2.4
Name: neo-whisper
Version: 0.0.3
Summary: Improve Whisper with RoPE and latest tokenizers of OpenAI
Home-page: https://github.com/kimang18/KrorngAI
Author: KHUN Kimang
Author-email: kimang.khun@polytechnique.org
Requires-Python: >=3.8
License-File: LICENSE
Dynamic: author
Dynamic: author-email
Dynamic: description
Dynamic: description-content-type
Dynamic: home-page
Dynamic: license-file
Dynamic: requires-python
Dynamic: summary
